xlsxlean/__init__.py
xlsxlean/reader.py
xlsxlean-0.1.0.dist-info/licenses/LICENSE
xlsxlean-0.1.0.dist-info/METADATA
xlsxlean-0.1.0.dist-info/WHEEL
xlsxlean-0.1.0.dist-info/top_level.txt
xlsxlean-0.1.0.dist-info/RECORD
