Metadata-Version: 2.4
Name: xlsxlean
Version: 0.1.0
Summary: Minimal memory XLSX reader with safe preview and full content options
Author: Animesh Ranjan
Author-email: ranjananimesh5@gmail.com
License: MIT
Classifier: Programming Language :: Python :: 3
Classifier: License :: OSI Approved :: MIT License
Classifier: Operating System :: OS Independent
Requires-Python: >=3.6
License-File: LICENSE
Requires-Dist: psutil
Dynamic: author
Dynamic: author-email
Dynamic: classifier
Dynamic: description
Dynamic: description-content-type
Dynamic: license
Dynamic: license-file
Dynamic: requires-dist
Dynamic: requires-python
Dynamic: summary
